mkdocs_latest_git_tag_plugin/__init__.py
mkdocs_latest_git_tag_plugin/plugin.py
mkdocs_latest_git_tag_plugin-0.1.2.dist-info/LICENSE.txt
mkdocs_latest_git_tag_plugin-0.1.2.dist-info/METADATA
mkdocs_latest_git_tag_plugin-0.1.2.dist-info/WHEEL
mkdocs_latest_git_tag_plugin-0.1.2.dist-info/entry_points.txt
mkdocs_latest_git_tag_plugin-0.1.2.dist-info/RECORD
