Metadata-Version: 2.1
Name: mkdocs-latest-git-tag-plugin
Version: 0.1.2
Summary: MkDocs plugin to get the latest git tag from the local repository
Home-page: https://github.com/seapagan/mkdocs-latest-git-tag-plugin
Author: Grant Ramsay
Author-email: seapagan@gmail.com
Requires-Python: >=3.8.1,<4.0.0
Classifier: Development Status :: 4 - Beta
Classifier: Environment :: Web Environment
Classifier: Intended Audience :: Developers
Classifier: License :: OSI Approved :: MIT License
Classifier: Operating System :: OS Independent
Classifier: Programming Language :: Python :: 3
Classifier: Programming Language :: Python :: 3.9
Classifier: Programming Language :: Python :: 3.10
Classifier: Programming Language :: Python :: 3.11
Classifier: Programming Language :: Python :: 3.12
Classifier: Programming Language :: Python :: 3.8
Classifier: Topic :: Documentation
Classifier: Topic :: Software Development :: Libraries
Classifier: Topic :: Software Development :: Libraries :: Python Modules
Classifier: Topic :: Text Processing :: Markup :: Markdown
Requires-Dist: gitpython (>=3.1.31,<4.0.0)
Requires-Dist: mkdocs (>=1.4.3,<2.0.0)
Project-URL: Bug Tracker, https://github.com/seapagan/mkdocs-latest-git-tag-plugin/issues
Project-URL: Pull Requests, https://github.com/seapagan/mkdocs-latest-git-tag-plugin/pulls
Project-URL: Repository, https://github.com/seapagan/mkdocs-latest-git-tag-plugin
